<?xml version="1.0" encoding="utf-8" ?>
<dwsync>
<file name="bg.jpg" server="ftp.mattkgross.com//" local="129964860000000000" remote="130672436400000000" />
<file name="button.png" server="ftp.mattkgross.com//" local="129964860000000000" remote="130672436400000000" />
<file name="counter_bg.png" server="ftp.mattkgross.com//" local="129964860000000000" remote="130672436400000000" />
<file name="deviantart.png" server="ftp.mattkgross.com//" local="129964860000000000" remote="130672436400000000" />
<file name="facebook.png" server="ftp.mattkgross.com//" local="129964860000000000" remote="130672436400000000" />
<file name="logo.png" server="ftp.mattkgross.com//" local="129964860000000000" remote="130672436400000000" />
<file name="logo.psd" server="ftp.mattkgross.com//" local="129968316000000000" remote="130672436400000000" />
<file name="logo_sample.png" server="ftp.mattkgross.com//" local="129964860000000000" remote="130672436400000000" />
<file name="mail-bg.png" server="ftp.mattkgross.com//" local="129964860000000000" remote="130672436400000000" />
<file name="next.png" server="ftp.mattkgross.com//" local="129964860000000000" remote="130672436400000000" />
<file name="page_background.png" server="ftp.mattkgross.com//" local="129964860000000000" remote="130672436400000000" />
<file name="prev.png" server="ftp.mattkgross.com//" local="129964860000000000" remote="130672436400000000" />
<file name="skype.png" server="ftp.mattkgross.com//" local="129964860000000000" remote="130672436400000000" />
<file name="stumbleupon.png" server="ftp.mattkgross.com//" local="129964860000000000" remote="130672436400000000" />
<file name="twitter.png" server="ftp.mattkgross.com//" local="129964860000000000" remote="130672436400000000" />
<file name="yahoo.png" server="ftp.mattkgross.com//" local="129964860000000000" remote="130672436400000000" />
<file name="youtube.png" server="ftp.mattkgross.com//" local="129964860000000000" remote="130672436400000000" />
</dwsync>